Workbook
Name Aporte: App!$D$16
Name investimento_mes: App!$C$31
Name patrimonio: App!$D$19
Name qtd_anos: App!$D$17
Name Rendimento_Carteira: App!$D$12
Name taxa_mensal: App!$D$18

Sheet App
B10: CONFIGURAÇÕES
B11: Salário | D11: 2000
B12: Rendimento de Carteira | D12: 0.01
B13: Sugestão de Investimento (30%) | D13: =D11*30% -> 600
B15: INVESTIMENTO MENSAL
B16: Quanto investir por mês? | D16: 200
B17: Por Quantos Anos? | D17: 4
B18: Taxa de Rendimento mensal? | D18: 0.01
B19: Patrimônio acumulado? | D19: =FV(taxa_mensal,qtd_anos*12,Aporte*-1) -> 12244.522
B20: Dividendos Mensais? | D20: =patrimonio*Rendimento_Carteira -> 122.44522
B22: CENÁRIOS POSSÍVEIS | D22: DIVIDENDOS
A23: 2 | B23: Patrimônio em 2 anos | C23: =FV($D$18,$A23*12,$D$16*-1) -> 5394.693 | D23: =C23*Rendimento_Carteira -> 53.94693
A24: 5 | B24: Patrimônio em 5 anos | C24: =FV($D$18,$A24*12,$D$16*-1) -> 16333.934 | D24: =C24*Rendimento_Carteira -> 163.33934
A25: 10 | B25: Patrimônio em 10 anos | C25: =FV($D$18,$A25*12,$D$16*-1) -> 46007.738 | D25: =C25*Rendimento_Carteira -> 460.07738
A26: 20 | B26: Patrimônio em 20 anos | C26: =FV($D$18,$A26*12,$D$16*-1) -> 197851.07 | D26: =C26*Rendimento_Carteira -> 1978.5107
A27: 30 | B27: Patrimônio em 30 anos | C27: =FV($D$18,$A27*12,$D$16*-1) -> 698992.83 | D27: =C27*Rendimento_Carteira -> 6989.9283
B30: PERFIL | C30: Conservador
B31: VALOR A SER INVESTIDO POR MÊS | C31: =Aporte -> 200
B34: TIPO DE FII | C34: PERCENTUAL SUGERIDO | D34: VALORES
B35: PAPEL | C35: =VLOOKUP(App!C30&"-"&App!B35,Apoio!$A$3:$D$20,4,FALSE) -> 0.3 | D35: =C35*investimento_mes -> 60
B36: TIJOLO | C36: =VLOOKUP(App!$C$30&"-"&App!B36,Apoio!$A$3:$D$20,4,FALSE) -> 0.5 | D36: =C36*investimento_mes -> 100
B37: HÍBRIDOS | C37: =VLOOKUP(App!$C$30&"-"&App!B37,Apoio!$A$3:$D$20,4,FALSE) -> 0.1 | D37: =C37*investimento_mes -> 20
B38: FOFs | C38: =VLOOKUP(App!$C$30&"-"&App!B38,Apoio!$A$3:$D$20,4,FALSE) -> 0.1 | D38: =C38*investimento_mes -> 20
B39: DESENVOLVIMENTO | C39: =VLOOKUP(App!$C$30&"-"&App!B39,Apoio!$A$3:$D$20,4,FALSE) -> 0 | D39: =C39*investimento_mes -> 0
B40: HOTELARIAS | C40: =VLOOKUP(App!$C$30&"-"&App!B40,Apoio!$A$3:$D$20,4,FALSE) -> 0 | D40: =C40*investimento_mes -> 0
D41: =SUM(D35:D40) -> 200

Sheet Apoio
A2: CHAVE | B2: PERFIL | C2: TIPO DE FII | D2: %
A3: =B3&"-"&C3 -> Conservador-PAPEL | B3: Conservador | C3: PAPEL | D3: 0.3
A4: =B4&"-"&C4 -> Conservador-TIJOLO | B4: Conservador | C4: TIJOLO | D4: 0.5
A5: =B5&"-"&C5 -> Conservador-HÍBRIDOS | B5: Conservador | C5: HÍBRIDOS | D5: 0.1
A6: =B6&"-"&C6 -> Conservador-FOFs | B6: Conservador | C6: FOFs | D6: 0.1
A7: =B7&"-"&C7 -> Conservador-DESENVOLVIMENTO | B7: Conservador | C7: DESENVOLVIMENTO | D7: 0
A8: =B8&"-"&C8 -> Conservador-HOTELARIAS | B8: Conservador | C8: HOTELARIAS | D8: 0
A9: =B9&"-"&C9 -> Moderado-PAPEL | B9: Moderado | C9: PAPEL | D9: 0.32
A10: =B10&"-"&C10 -> Moderado-TIJOLO | B10: Moderado | C10: TIJOLO | D10: 0.35
A11: =B11&"-"&C11 -> Moderado-HÍBRIDOS | B11: Moderado | C11: HÍBRIDOS | D11: 0.08
A12: =B12&"-"&C12 -> Moderado-FOFs | B12: Moderado | C12: FOFs | D12: 0.05
A13: =B13&"-"&C13 -> Moderado-DESENVOLVIMENTO | B13: Moderado | C13: DESENVOLVIMENTO | D13: 0.1
A14: =B14&"-"&C14 -> Moderado-HOTELARIAS | B14: Moderado | C14: HOTELARIAS | D14: 0.1
... A20: =B20&"-"&C20 -> Agressivo-HOTELARIAS | B20: Agressivo | C20: HOTELARIAS | D20: 0.1
